quivr_core/__init__.py
quivr_core/base_config.py
quivr_core/config.py
quivr_core/brain/__init__.py
quivr_core/brain/brain.py
quivr_core/brain/brain_defaults.py
quivr_core/brain/info.py
quivr_core/brain/serialization.py
quivr_core/files/__init__.py
quivr_core/files/file.py
quivr_core/llm/__init__.py
quivr_core/llm/llm_endpoint.py
quivr_core/llm_tools/__init__.py
quivr_core/llm_tools/entity.py
quivr_core/llm_tools/llm_tools.py
quivr_core/llm_tools/other_tools.py
quivr_core/llm_tools/web_search_tools.py
quivr_core/processor/__init__.py
quivr_core/processor/processor_base.py
quivr_core/processor/registry.py
quivr_core/processor/splitter.py
quivr_core/processor/implementations/__init__.py
quivr_core/processor/implementations/default.py
quivr_core/processor/implementations/megaparse_processor.py
quivr_core/processor/implementations/simple_txt_processor.py
quivr_core/processor/implementations/tika_processor.py
quivr_core/rag/__init__.py
quivr_core/rag/prompts.py
quivr_core/rag/quivr_rag.py
quivr_core/rag/quivr_rag_langgraph.py
quivr_core/rag/utils.py
quivr_core/rag/entities/__init__.py
quivr_core/rag/entities/chat.py
quivr_core/rag/entities/config.py
quivr_core/rag/entities/models.py
quivr_core/storage/__init__.py
quivr_core/storage/file.py
quivr_core/storage/local_storage.py
quivr_core/storage/storage_base.py
quivr_core-0.0.26.dist-info/METADATA
quivr_core-0.0.26.dist-info/WHEEL
quivr_core-0.0.26.dist-info/RECORD
