Metadata-Version: 2.3
Name: quivr-core
Version: 0.0.26
Summary: Quivr core RAG package
Author-email: Stan Girard <stan@quivr.app>
Requires-Python: >=3.11
Requires-Dist: aiofiles>=23.1.0
Requires-Dist: faiss-cpu>=1.8.0.post1
Requires-Dist: httpx>=0.27.0
Requires-Dist: langchain-anthropic>=0.1.23
Requires-Dist: langchain-cohere>=0.1.0
Requires-Dist: langchain-community>=0.2.12
Requires-Dist: langchain-core>=0.2.38
Requires-Dist: langchain-openai>=0.1.0
Requires-Dist: langchain<0.3.0,>=0.2.14
Requires-Dist: langgraph>=0.2.38
Requires-Dist: markupsafe>=2.1.5
Requires-Dist: megaparse-sdk==0.1.7
Requires-Dist: pydantic>=2.8.2
Requires-Dist: rapidfuzz>=3.10.1
Requires-Dist: rich>=13.7.1
Requires-Dist: tiktoken>=0.7.0
Requires-Dist: transformers[sentencepiece]>=4.44.2
Requires-Dist: types-pyyaml>=6.0.12.20240808
